sparsecubes/__init__.py
sparsecubes/__version__.py
sparsecubes/core.py
sparse_cubes-0.1.0.dist-info/LICENSE
sparse_cubes-0.1.0.dist-info/METADATA
sparse_cubes-0.1.0.dist-info/WHEEL
sparse_cubes-0.1.0.dist-info/top_level.txt
sparse_cubes-0.1.0.dist-info/RECORD
