Metadata-Version: 2.1
Name: sparse-cubes
Version: 0.1.0
Summary: Marching cubes on sparse matrices
Home-page: https://github.com/navis-org/sparse-cubes
Author: Philipp Schlegel
Author-email: pms70@cam.ac.uk
License: GNU GPL V3
Keywords: marching cubes sparse matrix voxel
Platform: UNKNOWN
Classifier: Development Status :: 3 - Alpha
Classifier: Intended Audience :: Science/Research
Classifier: Topic :: Scientific/Engineering :: Bio-Informatics
Classifier: License :: OSI Approved :: GNU General Public License v3 or later (GPLv3+)
Classifier: Programming Language :: Python :: 3
Classifier: Programming Language :: Python :: 3.7
Classifier: Programming Language :: Python :: 3.8
Classifier: Programming Language :: Python :: 3.9
Classifier: Programming Language :: Python :: 3.10
Requires-Python: >=3.7
License-File: LICENSE
Requires-Dist: numpy
Requires-Dist: trimesh
